whale_agent/__init__.py
whale_agent/cli.py
whale_agent/config.py
whale_agent/daemon.py
whale_agent/utils.py
whale_agent/collector/__init__.py
whale_agent/core/__init__.py
whale_agent/core/exceptions/__init__.py
whale_agent/core/exceptions/check.py
whale_agent/core/logging/__init__.py
whale_agent/core/logging/console.py
whale_agent/core/logging/file.py
whale_agent/core/logging/syslog.py
whale_agent/emitter/__init__.py
whale_agent/emitter/http.py
whale_agent/emitter/test_http_emitter.py
whale_agent-0.0.1.3.dist-info/DESCRIPTION.rst
whale_agent-0.0.1.3.dist-info/entry_points.txt
whale_agent-0.0.1.3.dist-info/METADATA
whale_agent-0.0.1.3.dist-info/metadata.json
whale_agent-0.0.1.3.dist-info/RECORD
whale_agent-0.0.1.3.dist-info/top_level.txt
whale_agent-0.0.1.3.dist-info/WHEEL
