Metadata-Version: 2.0
Name: whale-agent
Version: 0.0.1.3
Summary: Agent for Whale Monitoring
Home-page: https://github.com/WhaleMonitoring/agent/
Author: Whale Monitoring
Author-email: contact@whale.io
License: MIT
Keywords: Whale Monitoring,Agent,Monitoring,Alerting
Platform: UNKNOWN
Classifier: Development Status :: 2 - Pre-Alpha
Classifier: Intended Audience :: Developers
Classifier: License :: OSI Approved :: BSD License
Classifier: Natural Language :: English
Classifier: Programming Language :: Python :: 2
Classifier: Programming Language :: Python :: 2.7
Requires-Dist: requests
Requires-Dist: simplejson
Requires-Dist: pytz
Requires-Dist: pyaml
